humpty.py
humpty-0.2.1.dist-info/WHEEL
humpty-0.2.1.dist-info/top_level.txt
humpty-0.2.1.dist-info/DESCRIPTION.rst
humpty-0.2.1.dist-info/metadata.json
humpty-0.2.1.dist-info/METADATA
humpty-0.2.1.dist-info/entry_points.txt
humpty-0.2.1.dist-info/zip-safe
humpty-0.2.1.dist-info/RECORD
