Metadata-Version: 2.0
Name: humpty
Version: 0.2.1
Summary: A tool to convert python wheels to eggs
Home-page: https://github.com/dairiki/humpty
Author: Jeff Dairiki
Author-email: dairiki@dairiki.org
License: UNKNOWN
Keywords: python packaging wheel whl egg
Platform: UNKNOWN
Classifier: Development Status :: 4 - Beta
Classifier: Environment :: Console
Classifier: Intended Audience :: Developers
Classifier: Intended Audience :: System Administrators
Classifier: License :: OSI Approved :: BSD License
Classifier: Programming Language :: Python
Classifier: Topic :: System :: Archiving :: Packaging
Classifier: Topic :: System :: Software Distribution
Requires-Dist: click
Requires-Dist: distlib
Requires-Dist: setuptools
Requires-Dist: six
Provides-Extra: testing
Requires-Dist: pytest; extra == 'testing'
Requires-Dist: pytest-catchlog; extra == 'testing'
Requires-Dist: pkginfo; extra == 'testing'
Requires-Dist: virtualenv; extra == 'testing'
